example_package/__init__.py
example_package/example.py
SchoolSchedulerTest-0.0.1.dist-info/METADATA
SchoolSchedulerTest-0.0.1.dist-info/WHEEL
SchoolSchedulerTest-0.0.1.dist-info/top_level.txt
SchoolSchedulerTest-0.0.1.dist-info/RECORD
